Metadata-Version: 2.1
Name: TutorPy
Version: 1.0
Summary: TutorPy is a comprehensive Python module designed to assist learners at all levels—beginner, intermediate, and expert—in mastering the Python programming language. This module offers a combination of tutorials, practice exercises, and curated video links to provide a well-rounded learning experience
Author: Jamshaid Basit
